sbx_word_prediction_kb_bert/__init__.py
sbx_word_prediction_kb_bert/annotations.py
sbx_word_prediction_kb_bert/constants.py
sbx_word_prediction_kb_bert/metadata.yaml
sbx_word_prediction_kb_bert/predictor.py
sbx_word_prediction_kb_bert/py.typed
sparv_sbx_word_prediction_kb_bert-0.6.1.dist-info/METADATA
sparv_sbx_word_prediction_kb_bert-0.6.1.dist-info/WHEEL
sparv_sbx_word_prediction_kb_bert-0.6.1.dist-info/entry_points.txt
sparv_sbx_word_prediction_kb_bert-0.6.1.dist-info/RECORD
