Metadata-Version: 2.3
Name: sparv-sbx-word-prediction-kb-bert
Version: 0.6.1
Summary: A sparv plugin for computing word neighbours using a BERT model.
Project-URL: Homepage, https://spraakbanken.gu.se
Project-URL: Repository, https://github.com/spraakbanken/sparv-sbx-word-prediction
Project-URL: Bug Tracker, https://github.com/spraakbanken/sparv-sbx-word-prediction/labels/project%3Aword-prediction--kb-bert
Author-email: Kristoffer Andersson <kristoffer.andersson@gu.se>
License: MIT
Classifier: Development Status :: 4 - Beta
Classifier: Intended Audience :: Developers
Classifier: License :: OSI Approved :: MIT License
Classifier: Operating System :: POSIX
Classifier: Operating System :: Unix
Classifier: Programming Language :: Python :: 3.8
Classifier: Programming Language :: Python :: 3.9
Classifier: Programming Language :: Python :: 3.10
Classifier: Programming Language :: Python :: 3.11
Classifier: Programming Language :: Python :: Implementation :: CPython
Classifier: Topic :: Utilities
Requires-Python: >=3.9
Requires-Dist: sparv-pipeline>=5.2.0
Requires-Dist: torch>=2.3.1
Requires-Dist: transformers>=4.34.1
